subscription_vpetrov/__init__.py
subscription_vpetrov/config.py
subscription_vpetrov/crud.py
subscription_vpetrov/database.py
subscription_vpetrov/exceptions.py
subscription_vpetrov/models.py
subscription_vpetrov/schemas.py
subscription_vpetrov/validations.py
subscription_vpetrov-0.1.8.dist-info/LICENSE
subscription_vpetrov-0.1.8.dist-info/METADATA
subscription_vpetrov-0.1.8.dist-info/WHEEL
subscription_vpetrov-0.1.8.dist-info/top_level.txt
subscription_vpetrov-0.1.8.dist-info/RECORD
