Metadata-Version: 2.1
Name: subscription_vpetrov
Version: 0.1.8
License-File: LICENSE
Requires-Dist: fastapi
Requires-Dist: pydantic
Requires-Dist: sqlalchemy
Requires-Dist: alembic
Requires-Dist: email-validator
Requires-Dist: python-dateutil
